esteid_certificates/__init__.py
esteid_certificates/constants.py
esteid_certificates/files/DEMO_SK_TIMESTAMPING_AUTHORITY_2020.pem
esteid_certificates/files/EE_Certification_Centre_Root_CA.pem
esteid_certificates/files/EID-SK_2016.pem
esteid_certificates/files/EID_NQ_2021E.pem
esteid_certificates/files/EID_NQ_2021R.pem
esteid_certificates/files/EID_Q_2021E.pem
esteid_certificates/files/EID_Q_2021R.pem
esteid_certificates/files/EID_Q_2024E.pem
esteid_certificates/files/EID_Q_2024R.pem
esteid_certificates/files/ESTEID-SK_2015.pem
esteid_certificates/files/KLASS3-SK_2016_EECCRCA_SHA384.pem
esteid_certificates/files/NQ-SK_2016.pem
esteid_certificates/files/ORG_2021E.pem
esteid_certificates/files/ORG_2021R.pem
esteid_certificates/files/SK_TIMESTAMPING_AUTHORITY_2020.pem
esteid_certificates/files/SK_TIMESTAMPING_AUTHORITY_2021.pem
esteid_certificates/files/SK_TIMESTAMPING_AUTHORITY_2022.pem
esteid_certificates/files/SK_TIMESTAMPING_AUTHORITY_2023.pem
esteid_certificates/files/SK_TIMESTAMPING_UNIT_2024E.pem
esteid_certificates/files/SK_TIMESTAMPING_UNIT_2024R.pem
esteid_certificates/files/SK_TSA_CA_2023E.pem
esteid_certificates/files/SK_TSA_CA_2023R.pem
esteid_certificates/files/TEST of EID-SK 2016_reissued.pem
esteid_certificates/files/TEST of NQ-SK 2016_reissued.pem
esteid_certificates/files/TEST_EID-NQ_2021E.pem
esteid_certificates/files/TEST_EID-NQ_2021R.pem
esteid_certificates/files/TEST_EID-Q_2021E.pem
esteid_certificates/files/TEST_EID-Q_2021R.pem
esteid_certificates/files/TEST_ORG_2021E.pem
esteid_certificates/files/TEST_ORG_2021R.pem
esteid_certificates/files/TEST_SK_ROOT_G1_2021E.pem
esteid_certificates/files/TEST_SK_ROOT_G1_2021R.pem
esteid_certificates/files/TEST_of_EE-GovCA2018.pem
esteid_certificates/files/TEST_of_EE_Certification_Centre_Root_CA.pem
esteid_certificates/files/TEST_of_ESTEID-SK_2015.pem
esteid_certificates/files/TEST_of_ESTEID2018.pem
esteid_certificates/files/TEST_of_KLASS3-SK_2016.pem
esteid_certificates-1.0.2.dist-info/LICENCE.md
esteid_certificates-1.0.2.dist-info/METADATA
esteid_certificates-1.0.2.dist-info/WHEEL
esteid_certificates-1.0.2.dist-info/top_level.txt
esteid_certificates-1.0.2.dist-info/RECORD
