Metadata-Version: 2.1
Name: esteid-certificates
Version: 1.0.2
Summary: Certificates for Estonian e-identity services
Home-page: https://github.com/thorgate/esteid-certificates
Author: Thorgate
Author-email: info@thorgate.eu
License: ISC
Keywords: esteid asice xades smartid smart-id mobiilid mobileid mobile-id idcard
Classifier: Development Status :: 5 - Production/Stable
Classifier: Intended Audience :: Developers
Classifier: License :: OSI Approved :: BSD License
Classifier: Natural Language :: English
Classifier: Programming Language :: Python :: 3
Classifier: Programming Language :: Python :: 3.6
Classifier: Programming Language :: Python :: 3.7
Classifier: Programming Language :: Python :: 3.8
Classifier: Programming Language :: Python :: 3.9
Classifier: Programming Language :: Python :: 3.10
Classifier: Programming Language :: Python :: 3.11
Classifier: Programming Language :: Python :: 3.12
License-File: LICENCE.md
